{
    "defaultDownload": "https://mediafire.com/file/4fijmhv7ba2bpmm/AED1_Kicks.zip/",
    "defaultStream": "https://soundcloud.com/atxproducers/",
    "embedSoundcloud": "https://w.soundcloud.com/player/?url=https%3A//api.soundcloud.com/playlists/1806163063&color=%23233044/",
    "embedSpotify": "https://open.spotify.com/embed/playlist/1C6RBmscOMwLiEkdHgrfFi?theme=0/",
    "imageHero": "https://res.cloudinary.com/atxproducers/image/upload/q_auto/f_auto/defaults/hero.webp/",
    "imageMeetup": "https://res.cloudinary.com/atxproducers/image/upload/q_auto/f_auto/c_scale,w_500/defaults/meetup.webp/",
    "imageProducer": "https://res.cloudinary.com/atxproducers/image/upload/q_auto/f_auto/c_scale,h_150,w_150/defaults/producer.webp/",
    "imageSpotlight": "https://res.cloudinary.com/atxproducers/image/upload/q_auto/f_auto/c_scale,h_1000,w_1000/defaults/producer.webp/",
    "sponsorCapitalFactory": "https://capital-factory.officernd.com/signup?office=5d1bcda0dbd6e40010479eec/"
}